sdmxschemas/__init__.py
sdmxschemas/json/sdmx10/sdmx-json-data-schema.json
sdmxschemas/json/sdmx10/sdmx-json-metadata-schema.json
sdmxschemas/json/sdmx10/sdmx-json-structure-schema.json
sdmxschemas/json/sdmx20/sdmx-json-data-schema.json
sdmxschemas/json/sdmx20/sdmx-json-metadata-schema.json
sdmxschemas/json/sdmx20/sdmx-json-structure-schema.json
sdmxschemas/py.typed
sdmxschemas/xml/sdmx10/SDMXCommon.xsd
sdmxschemas/xml/sdmx10/SDMXCompactData.xsd
sdmxschemas/xml/sdmx10/SDMXCrossSectionalData.xsd
sdmxschemas/xml/sdmx10/SDMXGenericData.xsd
sdmxschemas/xml/sdmx10/SDMXMessage.xsd
sdmxschemas/xml/sdmx10/SDMXQuery.xsd
sdmxschemas/xml/sdmx10/SDMXStructure.xsd
sdmxschemas/xml/sdmx10/SDMXUtilityData.xsd
sdmxschemas/xml/sdmx10/xml.xsd
sdmxschemas/xml/sdmx20/SDMXCommon.xsd
sdmxschemas/xml/sdmx20/SDMXCompactData.xsd
sdmxschemas/xml/sdmx20/SDMXCrossSectionalData.xsd
sdmxschemas/xml/sdmx20/SDMXGenericData.xsd
sdmxschemas/xml/sdmx20/SDMXGenericMetadata.xsd
sdmxschemas/xml/sdmx20/SDMXMessage.xsd
sdmxschemas/xml/sdmx20/SDMXMetadataReport.xsd
sdmxschemas/xml/sdmx20/SDMXQuery.xsd
sdmxschemas/xml/sdmx20/SDMXRegistry.xsd
sdmxschemas/xml/sdmx20/SDMXStructure.xsd
sdmxschemas/xml/sdmx20/SDMXUtilityData.xsd
sdmxschemas/xml/sdmx20/xml.xsd
sdmxschemas/xml/sdmx21/SDMXCommon.xsd
sdmxschemas/xml/sdmx21/SDMXCommonReferences.xsd
sdmxschemas/xml/sdmx21/SDMXDataGeneric.xsd
sdmxschemas/xml/sdmx21/SDMXDataGenericBase.xsd
sdmxschemas/xml/sdmx21/SDMXDataGenericTimeSeries.xsd
sdmxschemas/xml/sdmx21/SDMXDataStructureSpecific.xsd
sdmxschemas/xml/sdmx21/SDMXDataStructureSpecificBase.xsd
sdmxschemas/xml/sdmx21/SDMXDataStructureSpecificTimeSeries.xsd
sdmxschemas/xml/sdmx21/SDMXMessage.xsd
sdmxschemas/xml/sdmx21/SDMXMessageFooter.xsd
sdmxschemas/xml/sdmx21/SDMXMetadataGeneric.xsd
sdmxschemas/xml/sdmx21/SDMXMetadataStructureSpecific.xsd
sdmxschemas/xml/sdmx21/SDMXQuery.xsd
sdmxschemas/xml/sdmx21/SDMXQueryBase.xsd
sdmxschemas/xml/sdmx21/SDMXQueryCategorisation.xsd
sdmxschemas/xml/sdmx21/SDMXQueryCategory.xsd
sdmxschemas-0.2.0.dist-info/LICENSE
sdmxschemas-0.2.0.dist-info/METADATA
sdmxschemas-0.2.0.dist-info/WHEEL
sdmxschemas-0.2.0.dist-info/RECORD
