Metadata-Version: 2.1
Name: sdmxschemas
Version: 0.2.0
Summary: SDMX schemas for Python
Home-page: https://github.com/Meaningful-Data/sdmx-schemas
License: Apache-2.0
Keywords: sdmx
Author: Francisco Javier Hernandez del Caño
Author-email: javier.hernandez@meaningfuldata.eu
Requires-Python: >=3.8,<4.0
Classifier: Development Status :: 4 - Beta
Classifier: Intended Audience :: Developers
Classifier: Intended Audience :: Science/Research
Classifier: License :: OSI Approved :: Apache Software License
Classifier: Programming Language :: Python :: 3
Classifier: Programming Language :: Python :: 3.8
Classifier: Programming Language :: Python :: 3.9
Classifier: Programming Language :: Python :: 3.10
Classifier: Programming Language :: Python :: 3.11
Classifier: Programming Language :: Python :: 3.12
Classifier: Typing :: Typed
Project-URL: Repository, https://github.com/Meaningful-Data/sdmx-schemas
